datek_web_crawler/__init__.py
datek_web_crawler/crawl.py
datek_web_crawler/py.typed
datek_web_crawler/types.py
datek_web_crawler/utils.py
datek_web_crawler/modules/__init__.py
datek_web_crawler/modules/page_analyzer.py
datek_web_crawler/modules/result_store.py
datek_web_crawler/modules/deduplicator/__init__.py
datek_web_crawler/modules/deduplicator/base.py
datek_web_crawler/modules/deduplicator/memory.py
datek_web_crawler/modules/page_downloader/__init__.py
datek_web_crawler/modules/page_downloader/base.py
datek_web_crawler/modules/page_downloader/httpx_downloader.py
datek_web_crawler/modules/page_store/__init__.py
datek_web_crawler/modules/page_store/base.py
datek_web_crawler/modules/page_store/filesystem.py
datek_web_crawler/modules/page_store/s3.py
datek_web_crawler/workers/__init__.py
datek_web_crawler/workers/analyzer.py
datek_web_crawler/workers/deduplicator.py
datek_web_crawler/workers/downloader.py
datek_web_crawler/workers/saver.py
datek_web_crawler/workers/status_logger.py
datek_web_crawler-0.1.0.dist-info/METADATA
datek_web_crawler-0.1.0.dist-info/WHEEL
datek_web_crawler-0.1.0.dist-info/licenses/LICENSE
datek_web_crawler-0.1.0.dist-info/RECORD
