Metadata-Version: 2.4
Name: datek-web-crawler
Version: 0.1.0
Summary: Simple, powerful web crawler
License-File: LICENSE
Requires-Python: >=3.13
Requires-Dist: lxml>=5.3.2
Requires-Dist: structlog>=25.2.0
Provides-Extra: httpx
Requires-Dist: httpx>=0.28.1; extra == 'httpx'
Provides-Extra: s3
Requires-Dist: boto3>=1.37.1; extra == 's3'
Requires-Dist: datek-app-utils>=0.4.0; extra == 's3'
Requires-Dist: types-boto3[s3]>=1.37.33; extra == 's3'
